source_s3/__init__.py
source_s3/exceptions.py
source_s3/run.py
source_s3/source.py
source_s3/source_files_abstract/__init__.py
source_s3/source_files_abstract/formats/__init__.py
source_s3/source_files_abstract/formats/avro_spec.py
source_s3/source_files_abstract/formats/csv_spec.py
source_s3/source_files_abstract/formats/jsonl_spec.py
source_s3/source_files_abstract/formats/parquet_spec.py
source_s3/source_files_abstract/source.py
source_s3/source_files_abstract/spec.py
source_s3/stream.py
source_s3/utils.py
source_s3/v4/__init__.py
source_s3/v4/config.py
source_s3/v4/cursor.py
source_s3/v4/legacy_config_transformer.py
source_s3/v4/source.py
source_s3/v4/stream_reader.py
source_s3/v4/zip_reader.py
airbyte_source_s3-4.15.2.dist-info/METADATA
airbyte_source_s3-4.15.2.dist-info/WHEEL
airbyte_source_s3-4.15.2.dist-info/entry_points.txt
airbyte_source_s3-4.15.2.dist-info/RECORD
